shex/__init__.py
shex/agent.py
shex/config.py
shex/i18n.py
shex/main.py
shex/paths.py
shex/tools.py
shex-0.1.6.dist-info/licenses/LICENSE
shex-0.1.6.dist-info/METADATA
shex-0.1.6.dist-info/WHEEL
shex-0.1.6.dist-info/entry_points.txt
shex-0.1.6.dist-info/top_level.txt
shex-0.1.6.dist-info/RECORD
