Metadata-Version: 2.4
Name: shex
Version: 0.1.6
Summary: Natural language command-line assistant powered by LLM
Author: yuhai
License: MIT
Project-URL: Homepage, https://github.com/YUHAI0/shex
Keywords: cli,llm,natural-language,command-line,assistant,ai,shell
Classifier: Development Status :: 4 - Beta
Classifier: Environment :: Console
Classifier: Intended Audience :: Developers
Classifier: License :: OSI Approved :: MIT License
Classifier: Operating System :: OS Independent
Classifier: Programming Language :: Python :: 3
Classifier: Programming Language :: Python :: 3.8
Classifier: Programming Language :: Python :: 3.9
Classifier: Programming Language :: Python :: 3.10
Classifier: Programming Language :: Python :: 3.11
Classifier: Programming Language :: Python :: 3.12
Classifier: Topic :: Utilities
Requires-Python: >=3.8
License-File: LICENSE
Requires-Dist: openai>=1.0.0
Requires-Dist: python-dotenv>=1.0.0
Dynamic: license-file
